torchdiffeq/__init__.py
torchdiffeq/_impl/__init__.py
torchdiffeq/_impl/adaptive_heun.py
torchdiffeq/_impl/adjoint.py
torchdiffeq/_impl/bosh3.py
torchdiffeq/_impl/dopri5.py
torchdiffeq/_impl/dopri8.py
torchdiffeq/_impl/event_handling.py
torchdiffeq/_impl/fehlberg2.py
torchdiffeq/_impl/fixed_adams.py
torchdiffeq/_impl/fixed_grid.py
torchdiffeq/_impl/interp.py
torchdiffeq/_impl/misc.py
torchdiffeq/_impl/odeint.py
torchdiffeq/_impl/rk_common.py
torchdiffeq/_impl/scipy_wrapper.py
torchdiffeq/_impl/solvers.py
torchdiffeq-0.2.5.dist-info/LICENSE
torchdiffeq-0.2.5.dist-info/METADATA
torchdiffeq-0.2.5.dist-info/WHEEL
torchdiffeq-0.2.5.dist-info/top_level.txt
torchdiffeq-0.2.5.dist-info/RECORD
